fileinit/__init__.py
fileinit/test.py
fileinit-0.0.2.dist-info/METADATA
fileinit-0.0.2.dist-info/WHEEL
fileinit-0.0.2.dist-info/top_level.txt
fileinit-0.0.2.dist-info/RECORD
